{
  "video_id": "zQLxbN8dxJg",
  "total_interventions": 14,
  "interventions": [
    {
      "id": "eeb254db-749f-4ca5-ab4a-bb2c35043bf5",
      "video_id": "zQLxbN8dxJg",
      "timestamp": 24.0,
      "timestamp_formatted": "00:24",
      "frame_path": "data\\zQLxbN8dxJg\\keyframes\\frame_0000_00_24.jpg",
      "content_type": "diagram",
      "complexity_score": 0.2828,
      "clip_confidence": 0.2828,
      "trigger_reason": "Deictic",
      "confidence": "medium",
      "transcript_context": "So, here's a question.",
      "is_bookmarked": false,
      "created_at": "2026-05-12T03:57:30.325593"
    },
    {
      "id": "f9bd5800-6c62-445d-a312-b0f00a33bbb8",
      "video_id": "zQLxbN8dxJg",
      "timestamp": 50.0,
      "timestamp_formatted": "00:50",
      "frame_path": "data\\zQLxbN8dxJg\\keyframes\\frame_0001_00_50.jpg",
      "content_type": "diagram",
      "complexity_score": 0.2902,
      "clip_confidence": 0.2902,
      "trigger_reason": "Unknown",
      "confidence": "low",
      "transcript_context": "should be a constant.",
      "is_bookmarked": false,
      "created_at": "2026-05-12T03:57:30.325632"
    },
    {
      "id": "c5432965-c25d-43d2-ad5e-ba9b77da5264",
      "video_id": "zQLxbN8dxJg",
      "timestamp": 72.0,
      "timestamp_formatted": "01:12",
      "frame_path": "data\\zQLxbN8dxJg\\keyframes\\frame_0002_01_12.jpg",
      "content_type": "equation",
      "complexity_score": 0.2856,
      "clip_confidence": 0.2856,
      "trigger_reason": "Unknown",
      "confidence": "low",
      "transcript_context": "It can apply to a system\nof particles as well.",
      "is_bookmarked": false,
      "created_at": "2026-05-12T03:57:30.325661"
    },
    {
      "id": "464f5f82-e54a-45ad-b14e-8e40d56b502c",
      "video_id": "zQLxbN8dxJg",
      "timestamp": 116.0,
      "timestamp_formatted": "01:56",
      "frame_path": "data\\zQLxbN8dxJg\\keyframes\\frame_0003_01_56.jpg",
      "content_type": "equation",
      "complexity_score": 0.3175,
      "clip_confidence": 0.3175,
      "trigger_reason": "High Complexity",
      "confidence": "medium",
      "transcript_context": "This is called the conservation\nof linear momentum,",
      "is_bookmarked": false,
      "created_at": "2026-05-12T03:57:30.325692"
    },
    {
      "id": "810a7079-1be4-4f35-863c-a60d9e448ee4",
      "video_id": "zQLxbN8dxJg",
      "timestamp": 146.0,
      "timestamp_formatted": "02:26",
      "frame_path": "data\\zQLxbN8dxJg\\keyframes\\frame_0004_02_26.jpg",
      "content_type": "diagram",
      "complexity_score": 0.3314,
      "clip_confidence": 0.3314,
      "trigger_reason": "High Complexity",
      "confidence": "medium",
      "transcript_context": "The particles are interacting\namongst themselves.",
      "is_bookmarked": false,
      "created_at": "2026-05-12T03:57:30.325720"
    },
    {
      "id": "5ff2ef4b-0ba8-408f-b754-67e4b1cc2a05",
      "video_id": "zQLxbN8dxJg",
      "timestamp": 192.0,
      "timestamp_formatted": "03:12",
      "frame_path": "data\\zQLxbN8dxJg\\keyframes\\frame_0005_03_12.jpg",
      "content_type": "diagram",
      "complexity_score": 0.331,
      "clip_confidence": 0.331,
      "trigger_reason": "Deictic + High Complexity",
      "confidence": "high",
      "transcript_context": "because there's another kind of momentum",
      "is_bookmarked": false,
      "created_at": "2026-05-12T03:57:30.325749"
    },
    {
      "id": "f0b7eca4-b9d9-491f-b45f-565ab317906e",
      "video_id": "zQLxbN8dxJg",
      "timestamp": 210.0,
      "timestamp_formatted": "03:30",
      "frame_path": "data\\zQLxbN8dxJg\\keyframes\\frame_0006_03_30.jpg",
      "content_type": "diagram",
      "complexity_score": 0.3309,
      "clip_confidence": 0.3309,
      "trigger_reason": "High Complexity",
      "confidence": "medium",
      "transcript_context": "Let's try to get an\nexpression for the velocity",
      "is_bookmarked": false,
      "created_at": "2026-05-12T03:57:30.325777"
    },
    {
      "id": "d554d874-ebf9-4c02-bc02-62f6e81ffbf0",
      "video_id": "zQLxbN8dxJg",
      "timestamp": 828.0,
      "timestamp_formatted": "13:48",
      "frame_path": "data\\zQLxbN8dxJg\\keyframes\\frame_0007_13_48.jpg",
      "content_type": "equation",
      "complexity_score": 0.3663,
      "clip_confidence": 0.3663,
      "trigger_reason": "High Complexity",
      "confidence": "medium",
      "transcript_context": "When one object puts a force on another,",
      "is_bookmarked": false,
      "created_at": "2026-05-12T03:57:30.325804"
    },
    {
      "id": "a8c284a0-067d-408f-af2b-f481799a4d9b",
      "video_id": "zQLxbN8dxJg",
      "timestamp": 834.0,
      "timestamp_formatted": "13:54",
      "frame_path": "data\\zQLxbN8dxJg\\keyframes\\frame_0010_13_54.jpg",
      "content_type": "equation",
      "complexity_score": 0.366,
      "clip_confidence": 0.366,
      "trigger_reason": "High Complexity",
      "confidence": "medium",
      "transcript_context": "So what's incredible",
      "is_bookmarked": false,
      "created_at": "2026-05-12T03:57:30.325830"
    },
    {
      "id": "1e84879e-3e51-4282-800c-bbf98fe22877",
      "video_id": "zQLxbN8dxJg",
      "timestamp": 840.0,
      "timestamp_formatted": "14:00",
      "frame_path": "data\\zQLxbN8dxJg\\keyframes\\frame_0012_14_00.jpg",
      "content_type": "equation",
      "complexity_score": 0.3661,
      "clip_confidence": 0.3661,
      "trigger_reason": "High Complexity",
      "confidence": "medium",
      "transcript_context": "or you can do it the other way around.",
      "is_bookmarked": false,
      "created_at": "2026-05-12T03:57:30.325855"
    },
    {
      "id": "fb4c2165-129e-4d6e-90a6-c4ee99c2d357",
      "video_id": "zQLxbN8dxJg",
      "timestamp": 846.0,
      "timestamp_formatted": "14:06",
      "frame_path": "data\\zQLxbN8dxJg\\keyframes\\frame_0015_14_06.jpg",
      "content_type": "equation",
      "complexity_score": 0.3664,
      "clip_confidence": 0.3664,
      "trigger_reason": "High Complexity",
      "confidence": "medium",
      "transcript_context": "So we can get some more intuition",
      "is_bookmarked": false,
      "created_at": "2026-05-12T03:57:30.325880"
    },
    {
      "id": "c3f3ab95-7961-48fa-b1a1-bf9a5b603690",
      "video_id": "zQLxbN8dxJg",
      "timestamp": 856.0,
      "timestamp_formatted": "14:16",
      "frame_path": "data\\zQLxbN8dxJg\\keyframes\\frame_0017_14_16.jpg",
      "content_type": "slide",
      "complexity_score": 0.3514,
      "clip_confidence": 0.3514,
      "trigger_reason": "High Complexity",
      "confidence": "medium",
      "transcript_context": "came from a German mathematician\nnamed Emmy Noether.",
      "is_bookmarked": false,
      "created_at": "2026-05-12T03:57:30.325905"
    },
    {
      "id": "90b7ed48-9308-4fc1-a2c9-b1194c6aa668",
      "video_id": "zQLxbN8dxJg",
      "timestamp": 890.0,
      "timestamp_formatted": "14:50",
      "frame_path": "data\\zQLxbN8dxJg\\keyframes\\frame_0018_14_50.jpg",
      "content_type": "equation",
      "complexity_score": 0.3723,
      "clip_confidence": 0.3723,
      "trigger_reason": "High Complexity",
      "confidence": "medium",
      "transcript_context": "whenever the net external\nforce on a system is 0,",
      "is_bookmarked": false,
      "created_at": "2026-05-12T03:57:30.325936"
    },
    {
      "id": "7aa2c33b-8539-4925-bfda-435d946a4d97",
      "video_id": "zQLxbN8dxJg",
      "timestamp": 896.0,
      "timestamp_formatted": "14:56",
      "frame_path": "data\\zQLxbN8dxJg\\keyframes\\frame_0020_14_56.jpg",
      "content_type": "equation",
      "complexity_score": 0.366,
      "clip_confidence": 0.366,
      "trigger_reason": "High Complexity",
      "confidence": "medium",
      "transcript_context": "the momentum of that system\nmust remain the same.",
      "is_bookmarked": false,
      "created_at": "2026-05-12T03:57:30.325963"
    }
  ],
  "created_at": "2026-05-12T03:57:30.340364"
}